pykeymapper/__init__.py
pykeymapper/cli.py
pykeymapper/events.py
pykeymapper/runner.py
pykeymapper/utils.py
pykeymapper/modifiers/__init__.py
pykeymapper/modifiers/base.py
pykeymapper/modifiers/custom_modifier.py
pykeymapper/modifiers/existing_modifier.py
pykeymapper/premade/__init__.py
pykeymapper/premade/alt_brackets.py
pykeymapper/premade/backslash2shift.py
pykeymapper/premade/forwardslash2shift.py
pykeymapper/premade/special_space.py
pykeymapper-0.1.3.dist-info/LICENSE
pykeymapper-0.1.3.dist-info/METADATA
pykeymapper-0.1.3.dist-info/WHEEL
pykeymapper-0.1.3.dist-info/entry_points.txt
pykeymapper-0.1.3.dist-info/top_level.txt
pykeymapper-0.1.3.dist-info/RECORD
