Metadata-Version: 2.1
Name: pykeymapper
Version: 0.1.3
Summary: A Python library with utilities to help contruct "interception" input manipulation flows.
Home-page: https://gitlab.com/sluenenglish/pykeymapper
Author: Samuel Luen-English
Author-email: sluenenglish@gmail.com
License: MIT license
Keywords: pykeymapper
Platform: UNKNOWN
Classifier: Development Status :: 2 - Pre-Alpha
Classifier: Intended Audience :: Developers
Classifier: License :: OSI Approved :: MIT License
Classifier: Natural Language :: English
Classifier: Programming Language :: Python :: 3
Classifier: Programming Language :: Python :: 3.6
Classifier: Programming Language :: Python :: 3.7
Classifier: Programming Language :: Python :: 3.8
Requires-Python: >=3.5
Requires-Dist: Click (>=7.0)
